fuckseashell/__init__.py
fuckseashell/download_assignment.py
fuckseashell/env.py
fuckseashell/extract_assignment.py
fuckseashell/fsrun.py
fuckseashell/fstest.py
fuckseashell-0.0.3.dist-info/LICENSE
fuckseashell-0.0.3.dist-info/METADATA
fuckseashell-0.0.3.dist-info/WHEEL
fuckseashell-0.0.3.dist-info/entry_points.txt
fuckseashell-0.0.3.dist-info/top_level.txt
fuckseashell-0.0.3.dist-info/RECORD
